{
   "name": "",
   "tests": 1,
   "failures": 0,
   "time": "37.900",
   "testsuite": [
     {
       "tests": 1,
       "failures": 0,
       "timestamp": "2024-03-11T23:22:20.740301877+01:00",
       "time": "27.250",
       "name": "./tests/k8s",
       "testcase": [
         {
           "classname": "k8s",
           "name": "0_validate_status",
           "timestamp": "2024-03-11T23:22:20.740874278+01:00",
           "time": "27.250",
           "assertions": 2
         }
       ]
     }
   ]
 }